dekartifacts-0.2.5.dist-info/METADATA
dekartifacts-0.2.5.dist-info/WHEEL
dekartifacts-0.2.5.dist-info/entry_points.txt
dekartifacts/allinone/__init__.py
dekartifacts/allinone/base/__init__.py
dekartifacts/allinone/docker.py
dekartifacts/allinone/helm.py
dekartifacts/allinone/staticfiles.py
dekartifacts/artifacts/__init__.py
dekartifacts/artifacts/base/__init__.py
dekartifacts/artifacts/docker.py
dekartifacts/artifacts/helm.py
dekartifacts/artifacts/staticfiles.py
dekartifacts/click/__entry__.py
dekartifacts/click/__init__.py
dekartifacts/click/docker/__entry__.py
dekartifacts/click/docker/__init__.py
dekartifacts/click/docker/aio.py
dekartifacts/click/docker/static.py
dekartifacts/click/helm.py
dekartifacts/click/registry/__entry__.py
dekartifacts/click/registry/__init__.py
dekartifacts/click/registry/docker.py
dekartifacts/click/registry/helm.py
dekartifacts/click/registry/staticfiles.py
dekartifacts/click/staticfiles.py
dekartifacts/dekshellplugin/__init__.py
dekartifacts/dekshellplugin/contexts/__init__.py
dekartifacts/registry/__init__.py
dekartifacts/registry/base/__init__.py
dekartifacts/registry/base/core.py
dekartifacts/registry/base/templatefiles/whl/(=(name)=)-(=(version)=).dist-info/METADATA
dekartifacts/registry/base/templatefiles/whl/(=(name)=)-(=(version)=).dist-info/RECORD
dekartifacts/registry/base/templatefiles/whl/(=(name)=)-(=(version)=).dist-info/WHEEL
dekartifacts/registry/base/templatefiles/whl/(=(name)=)/__init__.py
dekartifacts/registry/base/templatefiles/whl/.ignore
dekartifacts/registry/base/tmpl.py
dekartifacts/registry/docker.py
dekartifacts/registry/helm.py
dekartifacts/registry/staticfiles.py
dekartifacts/repo/__init__.py
dekartifacts/repo/helm.py
dekartifacts/repo/staticfiles.py
dekartifacts/tools/__init__.py
dekartifacts/tools/helm.py
dekartifacts-0.2.5.dist-info/RECORD
