Metadata-Version: 2.1
Name: dekartifacts
Version: 0.2.5
Author-Email: sanzenwin <sanzenwin@gmail.com>
License: MIT
Requires-Python: >=3.7
Requires-Dist: twine
Requires-Dist: virtualenv<21.0.0
Requires-Dist: dektools[fetch,ignore,version,yaml]<1.0.0
Requires-Dist: dekgen<1.0.0
